<?xml version="1.0" encoding="UTF-8"?>
<!DOCTYPE mapper PUBLIC "-//mybatis.org//DTD Mapper 3.0//EN" "http://mybatis.org/dtd/mybatis-3-mapper.dtd">
<mapper namespace="cn.edu.hzvtc.dao.EmployeeMapper">
    <resultMap id="BaseResultMap" type="cn.edu.hzvtc.entity.Employee">
        <!--
          WARNING - @mbg.generated
          This element is automatically generated by MyBatis Generator, do not modify.
          This element was generated on Mon May 25 18:08:25 CST 2020.
        -->
        <id column="id" jdbcType="INTEGER" property="id"/>
        <result column="emp_name" jdbcType="VARCHAR" property="empName"/>
        <result column="emp_gender" jdbcType="CHAR" property="empGender"/>
        <result column="emp_birthday" jdbcType="DATE" property="empBirthday"/>
        <result column="emp_email" jdbcType="VARCHAR" property="empEmail"/>
        <result column="emp_salary" jdbcType="REAL" property="empSalary"/>
        <result column="create_time" jdbcType="DATE" property="createTime"/>
        <result column="dept_id" jdbcType="INTEGER" property="deptId"/>
    </resultMap>
    <resultMap id="ResultMapWithDept" type="cn.edu.hzvtc.entity.Employee">
        <!--
          WARNING - @mbg.generated
          This element is automatically generated by MyBatis Generator, do not modify.
          This element was generated on Fri May 22 10:43:24 CST 2020.
        -->
        <id column="id" jdbcType="INTEGER" property="id"/>
        <result column="emp_name" jdbcType="VARCHAR" property="empName"/>
        <result column="emp_gender" jdbcType="CHAR" property="empGender"/>
        <result column="emp_birthday" jdbcType="TIMESTAMP" property="empBirthday"/>
        <result column="emp_email" jdbcType="VARCHAR" property="empEmail"/>
        <result column="emp_salary" jdbcType="INTEGER" property="empSalary"/>
        <result column="create_time" jdbcType="TIMESTAMP" property="createTime"/>
        <result column="dept_id" jdbcType="INTEGER" property="deptId"/>
        <association property="department" javaType="cn.edu.hzvtc.entity.Department">
            <id column="did" property="id"></id>
            <result column="dept_name" property="deptName"></result>
        </association>
    </resultMap>


    <delete id="deleteByPrimaryKey" parameterType="java.lang.Integer">
        <!--
          WARNING - @mbg.generated
          This element is automatically generated by MyBatis Generator, do not modify.
          This element was generated on Mon May 25 18:08:25 CST 2020.
        -->
        delete from tbl_emp
        where id = #{id,jdbcType=INTEGER}
    </delete>
    <insert id="insert" parameterType="cn.edu.hzvtc.entity.Employee">
        <!--
          WARNING - @mbg.generated
          This element is automatically generated by MyBatis Generator, do not modify.
          This element was generated on Mon May 25 18:08:25 CST 2020.
        -->
        insert into tbl_emp (id, emp_name, emp_gender,
        emp_birthday, emp_email, emp_salary,
        create_time, dept_id)
        values (#{id,jdbcType=INTEGER}, #{empName,jdbcType=VARCHAR}, #{empGender,jdbcType=CHAR},
        #{empBirthday,jdbcType=DATE}, #{empEmail,jdbcType=VARCHAR}, #{empSalary,jdbcType=REAL},
        #{createTime,jdbcType=DATE}, #{deptId,jdbcType=INTEGER})
    </insert>
    <update id="updateByPrimaryKey" parameterType="cn.edu.hzvtc.entity.Employee">
        <!--
          WARNING - @mbg.generated
          This element is automatically generated by MyBatis Generator, do not modify.
          This element was generated on Mon May 25 18:08:25 CST 2020.
        -->
        update tbl_emp
        <set>
            <if test="empName != null">
                emp_name = #{empName,jdbcType=VARCHAR},
            </if>
            <if test="empGender != null">
                emp_gender = #{empGender,jdbcType=CHAR},
            </if>
            <if test="empBirthday != null">
                emp_birthday = #{empBirthday,jdbcType=DATE},
            </if>
            <if test="empEmail != null">
                emp_email = #{empEmail,jdbcType=VARCHAR},
            </if>
            <if test="empSalary != null">
                emp_salary = #{empSalary,jdbcType=REAL},
            </if>
            <if test="empSalary != null">
                create_time = #{createTime,jdbcType=DATE},
            </if>
            <if test="empSalary != null">
                dept_id = #{deptId,jdbcType=INTEGER}
            </if>
        </set>
        where id = #{id,jdbcType=INTEGER}
    </update>
    <select id="selectByPrimaryKey" parameterType="java.lang.Integer" resultMap="ResultMapWithDept">
        <!--
          WARNING - @mbg.generated
          This element is automatically generated by MyBatis Generator, do not modify.
          This element was generated on Mon May 25 18:08:25 CST 2020.
        -->
        select e.id, e.emp_name, e.emp_gender, e.emp_birthday, e.emp_email, e.emp_salary, e.create_time,
        e.dept_id, d.id, d.dept_name
        from tbl_emp e
        left join tbl_dept d on e.dept_id = d.id
        where e.id = #{id,jdbcType=INTEGER}
    </select>
    <select id="selectAll" resultMap="BaseResultMap">
        <!--
          WARNING - @mbg.generated
          This element is automatically generated by MyBatis Generator, do not modify.
          This element was generated on Mon May 25 18:08:25 CST 2020.
        -->
        select id, emp_name, emp_gender, emp_birthday, emp_email, emp_salary, create_time,
        dept_id
        from tbl_emp
    </select>
    <select id="selectAllWithDept" resultMap="ResultMapWithDept">
   select e.id, emp_name, emp_gender, emp_birthday, emp_email, emp_salary, create_time,
      dept_id, d.id did,dept_name dept_name
      from tbl_emp e
      left join tbl_dept d on e.dept_id = d.id
      order by e.id desc
  </select>
    <delete id="deleteBatch">
        delete from tbl_emp
        <foreach collection="ids" item="e_id" separator="," open="where id in (" close=")">
            #{e_id}
        </foreach>
    </delete>

    <select id="selectByCondition" resultMap="ResultMapWithDept">
        select e.id, emp_name, emp_gender, emp_birthday, emp_email, emp_salary, create_time,
        dept_id, d.id did,dept_name dept_name
        from tbl_emp e
        left join tbl_dept d on e.dept_id = d.id
        <where>
            <if test="id != null">
                e.id = #{id}
            </if>
            <if test="empName != null and empName.trim() != &quot;&quot;">
                and e.emp_name = #{empName}
            </if>
        </where>
    </select>


</mapper>